exectrace/__init__.py
exectrace/msdos/__init__.py
exectrace/msx/__init__.py
exectrace-0.0.5.dist-info/METADATA
exectrace-0.0.5.dist-info/WHEEL
exectrace-0.0.5.dist-info/top_level.txt
exectrace-0.0.5.dist-info/RECORD
